llm_filesystem.py
llm_filesystem-2025.4.1.dist-info/licenses/LICENSE
llm_filesystem-2025.4.1.dist-info/METADATA
llm_filesystem-2025.4.1.dist-info/WHEEL
llm_filesystem-2025.4.1.dist-info/entry_points.txt
llm_filesystem-2025.4.1.dist-info/top_level.txt
llm_filesystem-2025.4.1.dist-info/RECORD
