Metadata-Version: 2.4
Name: llm-filesystem
Version: 2025.4.1
Summary: Load LLM templates from the filesystem
Author: Jeff Triplett
License: Apache-2.0
Project-URL: Homepage, https://github.com/jefftriplett/llm-filesystem
Project-URL: Changelog, https://github.com/jefftriplett/llm-filesystem/releases
Project-URL: Issues, https://github.com/jefftriplett/llm-filesystem/issues
Project-URL: CI, https://github.com/jefftriplett/llm-filesystem/actions
Classifier: License :: OSI Approved :: Apache Software License
Requires-Python: >=3.9
License-File: LICENSE
Requires-Dist: llm>=0.24
Provides-Extra: test
Requires-Dist: pytest; extra == "test"
Requires-Dist: pytest-httpx; extra == "test"
Dynamic: license-file
